{
    "163": [
        {
            "coin_id": "SOLUSDT",
            "trade_type": "futures",
            "side": "sell",
            "positionside": "long",
            "bot_id": 163,
            "status": "success",
            "order_type": "market",
            "amount": 0.1
        },
        {
            "coin_id": "BTCUSDT",
            "trade_type": "futures",
            "side": "sell",
            "positionside": "long",
            "bot_id": 163,
            "status": "success",
            "order_type": "market",
            "amount": 0.1
        }
    ]
}